black_percentage_tester/__init__.py
black_percentage_tester/__main__.py
black_percentage_tester-0.0.3.dist-info/METADATA
black_percentage_tester-0.0.3.dist-info/RECORD
black_percentage_tester-0.0.3.dist-info/WHEEL
black_percentage_tester-0.0.3.dist-info/entry_points.txt
black_percentage_tester-0.0.3.dist-info/top_level.txt
func/__init__.py
