Metadata-Version: 2.1
Name: black-percentage-tester
Version: 0.0.3
Summary: Black formatter percentage checker
Home-page: UNKNOWN
Author: Milan Suk
Author-email: milan.suk@kiwi.com
License: UNKNOWN
Platform: UNKNOWN
Requires-Dist: black
